Metadata-Version: 2.1
Name: pysqs-extended-client
Version: 0.0.1
Summary: Amazon SQS Extended Client Library for Python for sending large payloads that exceed sqs limitations via S3
Home-page: https://github.com/timothymugayi/boto3-sqs-extended-client-lib
Author: timothy.mugayi
Author-email: django.course@gmail.com
License: UNKNOWN
Keywords: SQS client python,SQS client,sqs extended client,aws sqs client,boto sqs client,large message sqs,sqs s3,sqs
Platform: any
Classifier: Environment :: Web Environment
Classifier: Intended Audience :: Developers
Classifier: License :: OSI Approved :: MIT License
Classifier: Operating System :: OS Independent
Classifier: Programming Language :: Python
Classifier: Programming Language :: Python :: 2.7
Classifier: Programming Language :: Python :: 3
Classifier: Programming Language :: Python :: 3.4
Classifier: Programming Language :: Python :: 3.5
Classifier: Programming Language :: Python :: 3.6
Classifier: Programming Language :: Python :: 3.7
Classifier: Programming Language :: Python :: Implementation :: CPython
Classifier: Programming Language :: Python :: Implementation :: PyPy
Classifier: Topic :: Internet :: WWW/HTTP :: Dynamic Content
Classifier: Topic :: Software Development :: Libraries :: Python Modules
